tno/sdg/graph/gen/graphbin/__init__.py
tno/sdg/graph/gen/graphbin/exceptions.py
tno/sdg/graph/gen/graphbin/graph.py
tno/sdg/graph/gen/graphbin/graphbin.py
tno/sdg/graph/gen/graphbin/py.typed
tno/sdg/graph/gen/graphbin/test/__init__.py
tno/sdg/graph/gen/graphbin/test/test_graphbin.py
tno/sdg/graph/gen/graphbin/utils/math.py
tno.sdg.graph.gen.graphbin-0.1.1.dist-info/LICENSE
tno.sdg.graph.gen.graphbin-0.1.1.dist-info/METADATA
tno.sdg.graph.gen.graphbin-0.1.1.dist-info/WHEEL
tno.sdg.graph.gen.graphbin-0.1.1.dist-info/top_level.txt
tno.sdg.graph.gen.graphbin-0.1.1.dist-info/RECORD
