Metadata-Version: 2.1
Name: tno.sdg.graph.gen.graphbin
Version: 0.1.1
Summary: GraphBin: a synthetic graph generator
Author-email: TNO PET Lab <petlab@tno.nl>
Maintainer-email: TNO PET Lab <petlab@tno.nl>
License: Apache License, Version 2.0
Project-URL: Homepage, https://pet.tno.nl/
Project-URL: Documentation, https://pet.tno.nl/sdg/graph/gen/graphbin/0.1.1
Project-URL: Source, https://github.com/TNO-SDG/graph.gen.graphbin
Keywords: TNO,SDG,synthetic data,synthetic data generation,graph
Platform: any
Classifier: License :: OSI Approved :: Apache Software License
Classifier: Programming Language :: Python :: 3
Classifier: Operating System :: OS Independent
Classifier: Intended Audience :: Developers
Classifier: Intended Audience :: Information Technology
Classifier: Intended Audience :: Science/Research
Classifier: Typing :: Typed
Classifier: Topic :: Scientific/Engineering
Requires-Python: >=3.8
License-File: LICENSE
Requires-Dist: numpy >=1.21
Requires-Dist: scipy >=1.9
Requires-Dist: scikit-learn >=1.1
Requires-Dist: pandas >=1.5
Provides-Extra: scripts
Requires-Dist: networkx >=2.8 ; extra == 'scripts'
Requires-Dist: matplotlib >=3.6 ; extra == 'scripts'
Provides-Extra: tests
Requires-Dist: pytest ; extra == 'tests'
